automated_marking/__init__.py
automated_marking/clone_utils.py
automated_marking/html_css_utils.py
automated_marking/java_utils.py
automated_marking/language_utils.py
automated_marking/logging_utils.py
automated_marking/main.py
automated_marking/repo_processing.py
automated_marking/sql_utils.py
automated_marking-0.1.7.dist-info/METADATA
automated_marking-0.1.7.dist-info/WHEEL
automated_marking-0.1.7.dist-info/entry_points.txt
automated_marking-0.1.7.dist-info/top_level.txt
automated_marking-0.1.7.dist-info/RECORD
